sott/__init__.py
sott/_modidx.py
sott/template.py
sott-0.0.5.dist-info/LICENSE
sott-0.0.5.dist-info/METADATA
sott-0.0.5.dist-info/WHEEL
sott-0.0.5.dist-info/entry_points.txt
sott-0.0.5.dist-info/top_level.txt
sott-0.0.5.dist-info/RECORD
