Metadata-Version: 2.1
Name: sott
Version: 0.0.5
Summary: Simple Offset Tracking Tool
Home-page: https://github.com/kanglcn/sott
Author: kanglcn
Author-email: kanglcn@gmail.com
License: GNU General Public License v3.0 only
Keywords: geoscience geophysics remote-sensing sar deformation
Classifier: Development Status :: 4 - Beta
Classifier: Intended Audience :: Developers
Classifier: Natural Language :: English
Classifier: Programming Language :: Python :: 3.7
Classifier: Programming Language :: Python :: 3.8
Classifier: Programming Language :: Python :: 3.9
Classifier: Programming Language :: Python :: 3.10
Classifier: License :: OSI Approved :: GNU General Public License v3 (GPLv3)
Requires-Python: >=3.7
License-File: LICENSE
Requires-Dist: numpy
Requires-Dist: scipy
Provides-Extra: dev
Requires-Dist: pre-commit ; extra == 'dev'
Requires-Dist: nbdev ; extra == 'dev'
Requires-Dist: dvc ; extra == 'dev'
